gp/bench/robot/BenchLibrary.py
gp/bench/robot/__init__.py
gp/bench/robot/测试台架.robot
gp_bench_client-0.0.1.dist-info/AUTHORS
gp_bench_client-0.0.1.dist-info/METADATA
gp_bench_client-0.0.1.dist-info/WHEEL
gp_bench_client-0.0.1.dist-info/pbr.json
gp_bench_client-0.0.1.dist-info/top_level.txt
gp_bench_client-0.0.1.dist-info/RECORD
